[
    {
        "name": "Dakar 2010",
        "filename": "dakar_2010_240x320.jar",
        "size": "450 KB"
    },
    {
        "name": "Prince of Persia: The Forgotten Sands",
        "filename": "prince_of_persia_the_sorgotten_sands_240x320_s40_rus.jar",
        "size": "908 KB"
    },
    {
        "name": "LocoRoco Hi",
        "filename": "LocoRocoHi.jar",
        "size": "426 KB"
    },
    {
        "name": "Doom 2 RPG",
        "filename": "doom2rpg.jar",
        "size": "790 KB"
    }
] 